{
  "body_background": {
    "color": "#17191e"
  },
  "secondary_font": {
    "family": "Unna",
    "font": "google"
  },
  "logo": 747,
  "logo_2x": 748,
  "logo_transparency": 747,
  "logo_transparency_2x": 748,
  "logo_mobile": 747,
  "logo_mobile_2x": 748,
  "header_layout": 8,
  "header_full_width": "no",
  "header_background": {
    "image": "\/\/javier.la-studioweb.com\/wp-content\/uploads\/2016\/12\/header-09-bg.jpg",
    "position": "center top",
    "repeat": "no-repeat",
    "size": "cover",
    "color": "rgba(0,0,0,0)"
  },
  "header_show_social": 1,
  "store_address": "845 Marvin Passage Suite 003, South Vitohaven",
  "store_phone": "(52) 765 123 890",
  "store_email": "info@la-studioweb.com",
  "page_header_layout": "hide",
  "footer_layout": 5,
  "footer_full_width": "no",
  "footer_copyright_text": "<div class=\"row\">\n\t<div class=\"col-xs-12 col-sm-7\" style=\"color:#585c68\">Copyright 2017 <span style=\"color:#b4b9c8\">Modern WooCommerce Theme<\/span>. Designed By <span style=\"color:#b4b9c8\">LA Studio<\/span><\/div>\n\t<div class=\"col-xs-12 col-sm-5 text-right\">\n\t\t<img src=\"\/\/javier.la-studioweb.com\/wp-content\/themes\/javier\/assets\/images\/footer-gateway.png\" alt=\"\">\n\t<\/div>\n<\/div>",
  "body_class": "home",
  "page_header_link_color": "#b5b7c4",
  "text_color": "#787a82",
  "heading_color": "#606a86",
  "primary_color": "#bb8462",
  "secondary_color": "#222222",
  "three_color": "#606a86",
  "border_color": "rgba(169,174,189,0.30)",
  "header_text_color": "#888888",
  "header_link_color": "#fff",
  "header_link_hover_color": "#bb8462",
  "mm_lv_1_color": "#fff",
  "mm_lv_1_bg_color": "rgba(0,0,0,0)",
  "mm_lv_1_hover_color": "#bb8462",
  "mm_lv_1_hover_bg_color": "rgba(0,0,0,0)",
  "header_transparency_text_color": "#fff",
  "header_transparency_link_color": "#fff",
  "header_transparency_link_hover_color": "#bb8462",
  "header_transparency_mm_lv_1_color": "#fff",
  "header_transparency_mm_lv_1_bg_color": "rgba(0,0,0,0)",
  "header_transparency_mm_lv_1_hover_color": "#bb8462",
  "header_transparency_mm_lv_1_hover_bg_color": "rgba(0,0,0,0)",
  "offcanvas_background": "#fff",
  "offcanvas_text_color": "#222222",
  "offcanvas_heading_color": "#222222",
  "offcanvas_link_color": "#222222",
  "offcanvas_link_hover_color": "#bb8462",
  "mm_dropdown_bg": "#fff",
  "mm_dropdown_link_color": "#696c75",
  "mm_dropdown_link_bg": "rgba(0,0,0,0)",
  "mm_dropdown_link_hover_color": "#222222",
  "mm_dropdown_link_hover_bg": "rgba(0,0,0,0)",
  "mm_wide_dropdown_bg": "#fff",
  "mm_wide_dropdown_heading_color": "#222222",
  "mm_wide_dropdown_link_color": "#696c75",
  "mm_wide_dropdown_link_bg": "rgba(0,0,0,0)",
  "mm_wide_dropdown_link_hover_color": "#222222",
  "mm_wide_dropdown_link_hover_bg": "rgba(0,0,0,0)",
  "mb_background": "#fff",
  "mb_lv_1_color": "#222222",
  "mb_lv_1_bg_color": "rgba(0,0,0,0)",
  "mb_lv_1_hover_color": "#fff",
  "mb_lv_1_hover_bg_color": "#bb8462",
  "mb_lv_2_color": "#222222",
  "mb_lv_2_bg_color": "rgba(0,0,0,0)",
  "mb_lv_2_hover_color": "#fff",
  "mb_lv_2_hover_bg_color": "#bb8462",
  "page_header_title_color": "#222222",
  "page_header_link_hover_color": "#222222",
  "footer_background":{
    "color": "#17191e"
  },
  "footer_text_color": "#606a86",
  "footer_heading_color": "#606a86",
  "footer_link_color": "#606a86",
  "footer_link_hover_color": "#fff"
}